aoc_cli_python/__init__.py
aoc_cli_python/getter.py
aoc_cli_python/initialiser.py
aoc_cli_python/language.py
aoc_cli_python/local_validations.py
aoc_cli_python/opener.py
aoc_cli_python/runner.py
aoc_cli_python/submitter.py
aoc_cli_python/resources/day.py
aoc_cli_python-0.0.6.dist-info/LICENSE
aoc_cli_python-0.0.6.dist-info/METADATA
aoc_cli_python-0.0.6.dist-info/WHEEL
aoc_cli_python-0.0.6.dist-info/entry_points.txt
aoc_cli_python-0.0.6.dist-info/top_level.txt
aoc_cli_python-0.0.6.dist-info/RECORD
